modicon/__init__.py
modicon/main.py
modicon-0.1.1.dist-info/METADATA
modicon-0.1.1.dist-info/WHEEL
modicon-0.1.1.dist-info/licenses/LICENSE
modicon-0.1.1.dist-info/RECORD
